visier_api_data_in/__init__.py
visier_api_data_in/py.typed
visier_api_data_in/api/__init__.py
visier_api_data_in/api/data_and_job_handling_api.py
visier_api_data_in/api/data_intake_api.py
visier_api_data_in/api/data_upload_api.py
visier_api_data_in/api/direct_data_intake_api.py
visier_api_data_in/api/pgp_key_api.py
visier_api_data_in/api/planning_data_load_api.py
visier_api_data_in/models/__init__.py
visier_api_data_in/models/admin_assign_connector_credentials_by_tenant_response_dto.py
visier_api_data_in/models/admin_assign_connector_credentials_response_dto.py
visier_api_data_in/models/admin_assign_connector_with_credentials_response_dto.py
visier_api_data_in/models/admin_assigned_credential_info_response_dto.py
visier_api_data_in/models/admin_connector_info_response_dto.py
visier_api_data_in/models/admin_connector_setting_request_dto.py
visier_api_data_in/models/admin_connector_setting_response_dto.py
visier_api_data_in/models/admin_connector_settings_response_dto.py
visier_api_data_in/models/admin_data_import_definition_apidto.py
visier_api_data_in/models/admin_data_import_definitions_apidto.py
visier_api_data_in/models/admin_data_version_and_date_dto.py
visier_api_data_in/models/admin_extractor_setting_apidto.py
visier_api_data_in/models/admin_extractor_setting_key_value_apidto.py
visier_api_data_in/models/admin_extractor_settings_apidto.py
visier_api_data_in/models/admin_jobs_consolidated_analytics_job_request_dto.py
visier_api_data_in/models/admin_jobs_extract_data_and_load_dto.py
visier_api_data_in/models/admin_jobs_processing_job_request_dto.py
visier_api_data_in/models/admin_multiple_tenant_data_versions_details_dto.py
visier_api_data_in/models/admin_multiple_tenant_data_versions_list_dto.py
visier_api_data_in/models/admin_set_connector_setting_request_dto.py
visier_api_data_in/models/admin_set_connector_setting_response_dto.py
visier_api_data_in/models/admin_set_connector_settings_request_dto.py
visier_api_data_in-22222222.99201.1906.dist-info/METADATA
visier_api_data_in-22222222.99201.1906.dist-info/WHEEL
visier_api_data_in-22222222.99201.1906.dist-info/top_level.txt
visier_api_data_in-22222222.99201.1906.dist-info/RECORD
