Metadata-Version: 2.4
Name: visier-api-data-in
Version: 22222222.99201.1906
Summary: Visier Data In APIs
Home-page: 
Author: Visier
Author-email: alpine@visier.com
License: Apache License, Version 2.0
Keywords: Visier,Visier-SDK,Visier Data In APIs
Requires-Dist: visier-api-core~=22222222.99201.1906
Dynamic: author
Dynamic: author-email
Dynamic: description
Dynamic: description-content-type
Dynamic: keywords
Dynamic: license
Dynamic: requires-dist
Dynamic: summary
